PyfodMC/__init__.py
PyfodMC/bonds.py
PyfodMC/cores.py
PyfodMC/database.py
PyfodMC/helperfunctions.py
PyfodMC/lones.py
PyfodMC/motifs.py
PyfodMC/pyfodmc.py
PyfodMC/version.py
docs/conf.py
docs/examples_builder.py
docs/_static/overview/make_images.py
pyfodmc-1.1.5.dist-info/licenses/LICENSE
pyfodmc-1.1.5.dist-info/METADATA
pyfodmc-1.1.5.dist-info/WHEEL
pyfodmc-1.1.5.dist-info/top_level.txt
pyfodmc-1.1.5.dist-info/RECORD
