Metadata-Version: 2.4
Name: PyfodMC
Version: 1.1.5
Summary: Python Fermi-orbital descriptor Monte-Carlo (PyfodMC)
Author-email: Kai Trepte <kai.trepte1987@gmail.com>
Project-URL: Repository, https://gitlab.com/opensic/PyfodMC
Project-URL: Issues, https://gitlab.com/opensic/PyfodMC/-/issues
Project-URL: Changelog, https://gitlab.com/opensic/PyfodMC/-/blob/main/CHANGELOG.md
Keywords: Python,FLO-SIC,FODs
Classifier: Development Status :: 5 - Production/Stable
Classifier: Intended Audience :: Developers
Classifier: Intended Audience :: Education
Classifier: Intended Audience :: Science/Research
Classifier: License :: OSI Approved
Classifier: License :: OSI Approved :: Apache Software License
Classifier: Operating System :: Unix
Classifier: Programming Language :: Python
Classifier: Programming Language :: Python :: 3
Classifier: Programming Language :: Python :: 3 :: Only
Classifier: Programming Language :: Python :: 3.6
Classifier: Programming Language :: Python :: 3.7
Classifier: Programming Language :: Python :: 3.8
Classifier: Programming Language :: Python :: 3.9
Classifier: Programming Language :: Python :: 3.10
Classifier: Programming Language :: Python :: 3.11
Classifier: Topic :: Education
Classifier: Topic :: Scientific/Engineering
Classifier: Topic :: Scientific/Engineering :: Chemistry
Classifier: Topic :: Scientific/Engineering :: Physics
Classifier: Topic :: Software Development
Requires-Python: >=3.6
License-File: LICENSE
Requires-Dist: numpy
Dynamic: license-file
